bluemoon/__init__.py
bluemoonai-0.0.0.dist-info/LICENSE
bluemoonai-0.0.0.dist-info/METADATA
bluemoonai-0.0.0.dist-info/WHEEL
bluemoonai-0.0.0.dist-info/top_level.txt
bluemoonai-0.0.0.dist-info/RECORD
